pyIcingaAPIChecks/__init__.py
pyIcingaAPIChecks/rest.py
pyIcingaAPIChecks/CiscoIntersight/__init__.py
pyIcingaAPIChecks/CiscoIntersight/alarms.py
pyIcingaAPIChecks/CiscoIntersight/intersight_auth.py
pyIcingaAPIChecks/CiscoIntersight/nodeopstatus.py
pyIcingaAPIChecks/CiscoIntersight/nodestatus.py
pyIcingaAPIChecks-0.0.6.dist-info/METADATA
pyIcingaAPIChecks-0.0.6.dist-info/WHEEL
pyIcingaAPIChecks-0.0.6.dist-info/top_level.txt
pyIcingaAPIChecks-0.0.6.dist-info/RECORD
